ramanfitter/__init__.py
ramanfitter/main.py
ramanfitter/mapper.py
ramanfitter-0.0.3.dist-info/LICENSE
ramanfitter-0.0.3.dist-info/METADATA
ramanfitter-0.0.3.dist-info/WHEEL
ramanfitter-0.0.3.dist-info/top_level.txt
ramanfitter-0.0.3.dist-info/RECORD
