Metadata-Version: 2.1
Name: ramanfitter
Version: 0.0.3
Summary: A Raman peak finder and model fitter
Home-page: https://github.com/pypa/sampleproject
Author: John Ferrier
Author-email: <jo.ferrier@northeastern.edu>
Project-URL: Bug Tracker, https://github.com/pypa/sampleproject/issues
Keywords: python,raman,fitter,raman fitter,lorentzian,gaussian,voigt
Classifier: Topic :: Scientific/Engineering :: Physics
Classifier: Topic :: Scientific/Engineering :: Chemistry
Classifier: Development Status :: 1 - Planning
Classifier: License :: OSI Approved :: MIT License
Classifier: Programming Language :: Python :: 3
Classifier: Operating System :: Microsoft :: Windows
Classifier: Operating System :: MacOS :: MacOS X
Classifier: Operating System :: Unix
Classifier: Intended Audience :: Science/Research
Classifier: Natural Language :: English
Requires-Python: >=3.6
License-File: LICENSE
Requires-Dist: numpy
Requires-Dist: scipy
Requires-Dist: matplotlib
Requires-Dist: lmfit
